secapka/__init__.py
secapka/__main__.py
secapka/cli.py
secapka/dex.py
secapka/export.py
secapka/manifest.py
secapka/report.py
secapka/sarif.py
secapka/utils.py
secapka/xapk.py
secapka-0.1.17.dist-info/licenses/LICENSE
secapka-0.1.17.dist-info/METADATA
secapka-0.1.17.dist-info/WHEEL
secapka-0.1.17.dist-info/entry_points.txt
secapka-0.1.17.dist-info/top_level.txt
secapka-0.1.17.dist-info/RECORD
