Metadata-Version: 2.4
Name: secapka
Version: 0.1.17
Summary: Secapka - Framework CLI d'analyse d'APK Android
Author: Pi3rrhUs
License: MIT License
Project-URL: Homepage, https://github.com/Pi3rrhUs/Secapka
Project-URL: Repository, https://github.com/Pi3rrhUs/Secapka
Project-URL: Issues, https://github.com/Pi3rrhUs/Secapka/issues
Project-URL: Changelog, https://github.com/Pi3rrhUs/Secapka/blob/main/CHANGELOG.md
Keywords: android,apk,security,static-analysis,sarif,cli
Classifier: Development Status :: 3 - Alpha
Classifier: Environment :: Console
Classifier: Intended Audience :: Developers
Classifier: Intended Audience :: Information Technology
Classifier: License :: OSI Approved :: MIT License
Classifier: Programming Language :: Python :: 3
Classifier: Programming Language :: Python :: 3 :: Only
Classifier: Programming Language :: Python :: 3.11
Classifier: Programming Language :: Python :: 3.12
Classifier: Programming Language :: Python :: 3.13
Classifier: Topic :: Security
Classifier: Topic :: Software Development :: Quality Assurance
Requires-Python: >=3.10
License-File: LICENSE
Requires-Dist: click>=8.1
Requires-Dist: androguard>=4.1
Requires-Dist: loguru>=0.7
Provides-Extra: dev
Requires-Dist: pytest>=9; extra == "dev"
Requires-Dist: ruff>=0.6; extra == "dev"
Dynamic: license-file
